LS48/Timer_broken.v
module Timer(
    input wire clk_1hz,    // 1Hz时钟
    input wire cnt_2hz,    // 2Hz时钟
    input wire cnt_4hz,    // 4Hz时钟
    input wire cnt_10hz,   // 10Hz时钟
    input wire rst_n,      // 复位（低有效）
    input wire en,         // 使能输出
    input wire key0,       // 启动正计时（秒表）
    input wire key1,       // 启动倒计时（定时器）
    input wire key2,       // 模式切换
    input wire key4,       // 暂停/继续
    input wire key5,       // 切换计时频率
    input wire key6,       // 切换精度显示
    input wire [3:0] ten,  // 设定时间十位
    input wire [3:0] one,  // 设定时间个位
    input wire pause,      // 外部暂停信号
    
    output wire [3:0] tens,    // 十位输出（0-5）
    output wire [3:0] ones,    // 个位输出（0-9）
    output wire [3:0] xiaoshu, // 小数位输出（0-9）
    output wire point,         // 小数点
    output wire led            // LED闪烁
);

    // 内部寄存器
    reg [3:0] tens_reg;
    reg [3:0] ones_reg;
    reg [3:0] xiaoshu_reg;
    reg point_reg;
    reg led_reg;
    
    // 控制信号
    reg mode;              // 0=正计时, 1=倒计时
    reg running;           // 运行状态
    reg [2:0] freq_sel;    // 频率选择 0=1Hz, 1=2Hz, 2=4Hz
    reg precision_mode;    // 精度模式 0=秒, 1=0.1秒
    
    // 按键边沿检测
    reg key0_last, key1_last, key2_last, key4_last, key5_last, key6_last;
    wire key0_up, key1_up, key2_up, key4_up, key5_up, key6_up;
    
    // LED闪烁计数器
    reg [3:0] led_count;
    reg led_toggle;
    
    // 时钟选择
    wire selected_clk;
    
    // 输出赋值
    assign tens = tens_reg;
    assign ones = ones_reg;
    assign xiaoshu = xiaoshu_reg;
    assign point = point_reg;
    assign led = led_reg;
    
    // 时钟选择逻辑
    assign selected_clk = precision_mode ? cnt_10hz :
                         (freq_sel == 0) ? clk_1hz :
                         (freq_sel == 1) ? cnt_2hz :
                         (freq_sel == 2) ? cnt_4hz : clk_1hz;
    
    // 按键边沿检测
    always @(posedge selected_clk) begin
        key0_last <= key0;
        key1_last <= key1;
        key2_last <= key2;
        key4_last <= key4;
        key5_last <= key5;
        key6_last <= key6;
    end
    
    assign key0_up = key0 && (!key0_last);
    assign key1_up = key1 && (!key1_last);
    assign key2_up = key2 && (!key2_last);
    assign key4_up = key4 && (!key4_last);
    assign key5_up = key5 && (!key5_last);
    assign key6_up = key6 && (!key6_last);
    
    // 主控制逻辑
    always @(posedge selected_clk or negedge rst_n) begin
        if (!rst_n) begin
            // 复位状态
            tens_reg <= 4'd0;
            ones_reg <= 4'd0;
            xiaoshu_reg <= 4'd0;
            point_reg <= 1'b0;
            led_reg <= 1'b0;
            mode <= 1'b0;
            running <= 1'b0;
            freq_sel <= 3'd0;
            precision_mode <= 1'b0;
            led_count <= 4'd0;
            led_toggle <= 1'b0;
        end else if (!en) begin
            // 禁用状态
            tens_reg <= 4'd0;
            ones_reg <= 4'd0;
            xiaoshu_reg <= 4'd0;
            point_reg <= 1'b0;
            led_reg <= 1'b0;
            running <= 1'b0;
        end else begin
            // 按键处理
            
            // KEY0: 启动正计时（秒表）
            if (key0_up) begin
                mode <= 1'b0;          // 正计时模式
                running <= 1'b1;       // 开始运行
                tens_reg <= 4'd0;      // 从00.0开始
                ones_reg <= 4'd0;
                xiaoshu_reg <= 4'd0;
                led_reg <= 1'b0;
            end
            
            // KEY1: 启动倒计时（定时器）
            if (key1_up) begin
                mode <= 1'b1;          // 倒计时模式
                running <= 1'b1;       // 开始运行
                tens_reg <= ten;       // 从设定时间开始
                ones_reg <= one;
                xiaoshu_reg <= 4'd0;
                led_reg <= 1'b0;
                led_count <= 4'd0;
            end
            
            // KEY2: 模式切换
            if (key2_up) begin
                mode <= ~mode;
                running <= 1'b0;       // 停止运行
            end
            
            // KEY4: 暂停/继续
            if (key4_up) begin
                running <= ~running;
            end
            
            // 外部暂停信号
            if (pause) begin
                running <= 1'b0;
            end
            
            // KEY5: 切换计时频率
            if (key5_up) begin
                freq_sel <= (freq_sel >= 2) ? 3'd0 : freq_sel + 1;
            end
            
            // KEY6: 切换精度显示
            if (key6_up) begin
                precision_mode <= ~precision_mode;
                point_reg <= ~precision_mode;  // 精度模式时显示小数点
            end
            
            // 计时逻辑
            if (running) begin
                if (mode == 1'b0) begin
                    // 正计时模式（秒表）
                    if (precision_mode) begin
                        // 0.1秒精度
                        if (xiaoshu_reg < 9) begin
                            xiaoshu_reg <= xiaoshu_reg + 1;
                        end else begin
                            xiaoshu_reg <= 4'd0;
                            if (ones_reg < 9) begin
                                ones_reg <= ones_reg + 1;
                            end else begin
                                ones_reg <= 4'd0;
                                if (tens_reg < 5) begin
                                    tens_reg <= tens_reg + 1;
                                end else begin
                                    tens_reg <= 4'd0;  // 60秒后重新开始
                                end
                            end
                        end
                    end else begin
                        // 1秒精度
                        xiaoshu_reg <= 4'd0;
                        if (ones_reg < 9) begin
                            ones_reg <= ones_reg + 1;
                        end else begin
                            ones_reg <= 4'd0;
                            if (tens_reg < 5) begin
                                tens_reg <= tens_reg + 1;
                            end else begin
                                tens_reg <= 4'd0;  // 60秒后重新开始
                            end
                        end
                    end
                end else begin
                    // 倒计时模式（定时器）
                    if (precision_mode) begin
                        // 0.1秒精度
                        if (xiaoshu_reg > 0) begin
                            xiaoshu_reg <= xiaoshu_reg - 1;
                        end else begin
                            xiaoshu_reg <= 4'd9;
                            if (ones_reg > 0) begin
                                ones_reg <= ones_reg - 1;
                            end else begin
                                ones_reg <= 4'd9;
                                if (tens_reg > 0) begin
                                    tens_reg <= tens_reg - 1;
                                end else begin
                                    // 倒计时结束
                                    tens_reg <= 4'd0;
                                    ones_reg <= 4'd0;
                                    xiaoshu_reg <= 4'd0;
                                    running <= 1'b0;
                                end
                            end
                        end
                    end else begin
                        // 1秒精度
                        xiaoshu_reg <= 4'd0;
                        if (ones_reg > 0) begin
                            ones_reg <= ones_reg - 1;
                        end else begin
                            ones_reg <= 4'd9;
                            if (tens_reg > 0) begin
                                tens_reg <= tens_reg - 1;
                            end else begin
                                // 倒计时结束
                                tens_reg <= 4'd0;
                                ones_reg <= 4'd0;
                                running <= 1'b0;
                            end
                        end
                    end
                    
                    // LED闪烁逻辑（倒计时模式下时间<8秒时）
                    if (tens_reg == 0 && ones_reg < 8) begin
                        led_count <= led_count + 1;
                        if (led_count >= 4) begin  // 每0.4秒切换一次
                            led_count <= 4'd0;
                            led_toggle <= ~led_toggle;
                            led_reg <= led_toggle;
                        end
                    end else begin
                        led_reg <= 1'b0;
                        led_count <= 4'd0;
                        led_toggle <= 1'b0;
                    end
                end
            end
        end
    end

endmodule

LS48/tb_timer_simple.v
`timescale 1ns / 1ps

module tb_timer_simple;

    // 输入信号
    reg clk_1hz, cnt_2hz, cnt_4hz, cnt_10hz;
    reg rst_n, en;
    reg key0, key1, key2, key4, key5, key6;
    reg [3:0] ten, one;
    reg pause;
    
    // 输出信号
    wire [3:0] tens, ones, xiaoshu;
    wire point, led;
    
    // 实例化Timer模块
    Timer uut (
        .clk_1hz(clk_1hz),
        .cnt_2hz(cnt_2hz),
        .cnt_4hz(cnt_4hz),
        .cnt_10hz(cnt_10hz),
        .rst_n(rst_n),
        .en(en),
        .key0(key0),
        .key1(key1),
        .key2(key2),
        .key4(key4),
        .key5(key5),
        .key6(key6),
        .ten(ten),
        .one(one),
        .pause(pause),
        .tens(tens),
        .ones(ones),
        .xiaoshu(xiaoshu),
        .point(point),
        .led(led)
    );
    
    // 生成时钟信号
    initial begin
        clk_1hz = 0;
        cnt_2hz = 0;
        cnt_4hz = 0;
        cnt_10hz = 0;
        
        forever begin
            #50 cnt_10hz = ~cnt_10hz;   // 10Hz: 100ns周期
        end
    end
    
    always begin
        #125 cnt_4hz = ~cnt_4hz;        // 4Hz: 250ns周期
    end
    
    always begin
        #250 cnt_2hz = ~cnt_2hz;        // 2Hz: 500ns周期
    end
    
    always begin
        #500 clk_1hz = ~clk_1hz;        // 1Hz: 1000ns周期
    end
    
    // 测试序列
    initial begin
        // 生成波形文件
        $dumpfile("timer_simple.vcd");
        $dumpvars(0, tb_timer_simple);
        
        $display("=== Timer模块功能测试 ===");
        
        // 初始化
        rst_n = 0;
        en = 0;
        key0 = 1; key1 = 1; key2 = 1; key4 = 1; key5 = 1; key6 = 1;
        ten = 4'd1; one = 4'd5;  // 设定15秒
        pause = 0;
        
        #100;
        rst_n = 1;
        en = 1;
        $display("时间: %0t - 系统复位完成", $time);
        
        #200;
        
        // 测试1: 正计时模式
        $display("\n=== 测试正计时模式 ===");
        key0 = 0; #50; key0 = 1;  // 按下并释放KEY0
        $display("时间: %0t - 启动正计时", $time);
        
        // 观察几个时钟周期
        repeat(5) begin
            @(posedge clk_1hz);
            $display("时间: %0t - 正计时: %0d%0d.%0d, point=%b, led=%b", 
                     $time, tens, ones, xiaoshu, point, led);
        end
        
        // 测试精度模式
        $display("\n--- 切换到精度模式 ---");
        key6 = 0; #50; key6 = 1;  // 切换精度
        $display("时间: %0t - 切换到0.1秒精度", $time);
        
        repeat(10) begin
            @(posedge cnt_10hz);
            $display("时间: %0t - 高精度: %0d%0d.%0d, point=%b", 
                     $time, tens, ones, xiaoshu, point);
        end
        
        // 测试暂停
        $display("\n--- 测试暂停功能 ---");
        key4 = 0; #50; key4 = 1;  // 暂停
        $display("时间: %0t - 暂停计时", $time);
        
        repeat(3) begin
            @(posedge cnt_10hz);
            $display("时间: %0t - 暂停中: %0d%0d.%0d", 
                     $time, tens, ones, xiaoshu);
        end
        
        key4 = 0; #50; key4 = 1;  // 继续
        $display("时间: %0t - 继续计时", $time);
        
        repeat(5) begin
            @(posedge cnt_10hz);
            $display("时间: %0t - 继续: %0d%0d.%0d", 
                     $time, tens, ones, xiaoshu);
        end
        
        // 测试2: 倒计时模式
        $display("\n=== 测试倒计时模式 ===");
        key1 = 0; #50; key1 = 1;  // 启动倒计时
        $display("时间: %0t - 启动倒计时，初始: %0d%0d", $time, ten, one);
        
        repeat(8) begin
            @(posedge clk_1hz);
            $display("时间: %0t - 倒计时: %0d%0d.%0d, led=%b", 
                     $time, tens, ones, xiaoshu, led);
        end
        
        $display("\n=== 测试完成 ===");
        $finish;
    end

endmodule

LS48/timer_simple.vcd
$date
	Sun Jun  8 07:51:30 2025
$end
$version
	Icarus Verilog
$end
$timescale
	1ps
$end
$scope module tb_timer_simple $end
$var wire 4 ! xiaoshu [3:0] $end
$var wire 4 " tens [3:0] $end
$var wire 1 # point $end
$var wire 4 $ ones [3:0] $end
$var wire 1 % led $end
$var reg 1 & clk_1hz $end
$var reg 1 ' cnt_10hz $end
$var reg 1 ( cnt_2hz $end
$var reg 1 ) cnt_4hz $end
$var reg 1 * en $end
$var reg 1 + key0 $end
$var reg 1 , key1 $end
$var reg 1 - key2 $end
$var reg 1 . key4 $end
$var reg 1 / key5 $end
$var reg 1 0 key6 $end
$var reg 4 1 one [3:0] $end
$var reg 1 2 pause $end
$var reg 1 3 rst_n $end
$var reg 4 4 ten [3:0] $end
$scope module uut $end
$var wire 1 & clk_1hz $end
$var wire 1 ' cnt_10hz $end
$var wire 1 ( cnt_2hz $end
$var wire 1 ) cnt_4hz $end
$var wire 1 * en $end
$var wire 1 + key0 $end
$var wire 1 5 key0_up $end
$var wire 1 , key1 $end
$var wire 1 6 key1_up $end
$var wire 1 - key2 $end
$var wire 1 7 key2_up $end
$var wire 1 . key4 $end
$var wire 1 8 key4_up $end
$var wire 1 / key5 $end
$var wire 1 9 key5_up $end
$var wire 1 0 key6 $end
$var wire 1 : key6_up $end
$var wire 1 % led $end
$var wire 4 ; one [3:0] $end
$var wire 4 < ones [3:0] $end
$var wire 1 2 pause $end
$var wire 1 # point $end
$var wire 1 3 rst_n $end
$var wire 4 = ten [3:0] $end
$var wire 4 > tens [3:0] $end
$var wire 4 ? xiaoshu [3:0] $end
$var wire 1 @ selected_clk $end
$var reg 3 A freq_sel [2:0] $end
$var reg 1 B key0_last $end
$var reg 1 C key1_last $end
$var reg 1 D key2_last $end
$var reg 1 E key4_last $end
$var reg 1 F key5_last $end
$var reg 1 G key6_last $end
$var reg 4 H led_count [3:0] $end
$var reg 1 I led_reg $end
$var reg 1 J led_toggle $end
$var reg 1 K mode $end
$var reg 4 L ones_reg [3:0] $end
$var reg 1 M point_reg $end
$var reg 1 N precision_mode $end
$var reg 1 O running $end
$var reg 4 P tens_reg [3:0] $end
$var reg 4 Q xiaoshu_reg [3:0] $end
$upscope $end
$upscope $end
$enddefinitions $end
#0
$dumpvars
b0 Q
b0 P
0O
0N
0M
b0 L
0K
0J
0I
b0 H
xG
xF
xE
xD
xC
xB
b0 A
0@
b0 ?
b0 >
b1 =
b0 <
b101 ;
x:
x9
x8
x7
x6
x5
b1 4
03
02
b101 1
10
1/
1.
1-
1,
1+
0*
0)
0(
0'
0&
0%
b0 $
0#
b0 "
b0 !
$end
#50000
1'
#100000
0'
1*
13
#125000
1)
#150000
1'
#200000
0'
#250000
1'
0)
1(
#300000
05
0'
0+
#350000
x5
1'
1+
#375000
1)
#400000
0'
#450000
1'
#500000
0:
09
08
07
06
05
1G
1F
1E
1D
1C
1B
1@
0'
0)
0(
1&
#550000
1'
#600000
0'
#625000
1)
#650000
1'
#700000
0'
#750000
1'
0)
1(
#800000
0'
#850000
1'
#875000
1)
#900000
0'
#950000
1'
#1000000
0@
0'
0)
0(
0&
#1050000
1'
#1100000
0'
#1125000
1)
#1150000
1'
#1200000
0'
#1250000
1'
0)
1(
#1300000
0'
#1350000
1'
#1375000
1)
#1400000
0'
#1450000
1'
#1500000
1@
0'
0)
0(
1&
#1550000
1'
#1600000
0'
#1625000
1)
#1650000
1'
#1700000
0'
#1750000
1'
0)
1(
#1800000
0'
#1850000
1'
#1875000
1)
#1900000
0'
#1950000
1'
#2000000
0@
0'
0)
0(
0&
#2050000
1'
#2100000
0'
#2125000
1)
#2150000
1'
#2200000
0'
#2250000
1'
0)
1(
#2300000
0'
#2350000
1'
#2375000
1)
#2400000
0'
#2450000
1'
#2500000
1@
0'
0)
0(
1&
#2550000
1'
#2600000
0'
#2625000
1)
#2650000
1'
#2700000
0'
#2750000
1'
0)
1(
#2800000
0'
#2850000
1'
#2875000
1)
#2900000
0'
#2950000
1'
#3000000
0@
0'
0)
0(
0&
#3050000
1'
#3100000
0'
#3125000
1)
#3150000
1'
#3200000
0'
#3250000
1'
0)
1(
#3300000
0'
#3350000
1'
#3375000
1)
#3400000
0'
#3450000
1'
#3500000
1@
0'
0)
0(
1&
#3550000
1'
#3600000
0'
#3625000
1)
#3650000
1'
#3700000
0'
#3750000
1'
0)
1(
#3800000
0'
#3850000
1'
#3875000
1)
#3900000
0'
#3950000
1'
#4000000
0@
0'
0)
0(
0&
#4050000
1'
#4100000
0'
#4125000
1)
#4150000
1'
#4200000
0'
#4250000
1'
0)
1(
#4300000
0'
#4350000
1'
#4375000
1)
#4400000
0'
#4450000
1'
#4500000
0G
1@
00
0'
0)
0(
1&
#4550000
1:
10
1'
#4600000
0'
#4625000
1)
#4650000
1'
#4700000
0'
#4750000
1'
0)
1(
#4800000
0'
#4850000
1'
#4875000
1)
#4900000
0'
#4950000
1'
#5000000
0@
0'
0)
0(
0&
#5050000
1'
#5100000
0'
#5125000
1)
#5150000
1'
#5200000
0'
#5250000
1'
0)
1(
#5300000
0'
#5350000
1'
#5375000
1)
#5400000
0'
#5450000
1'
#5500000
0:
1#
1M
1N
1G
0@
0'
0)
0(
1&
#5550000
0E
1@
0.
1'
#5600000
18
0@
1.
0'
#5625000
1)
#5650000
08
1O
1E
1@
1'
#5700000
0@
0'
#5750000
b1 !
b1 ?
b1 Q
1@
1'
0)
1(
#5800000
0@
0'
#5850000
b10 !
b10 ?
b10 Q
0E
1@
0.
1'
#5875000
1)
#5900000
18
0@
1.
0'
#5950000
08
b11 !
b11 ?
b11 Q
0O
1E
1@
1'
#6000000
0@
0'
0)
0(
0&
#6050000
1@
1'
#6100000
0@
0'
#6125000
1)
#6150000
1@
1'
#6200000
0@
0'
#6250000
1@
1'
0)
1(
#6300000
0@
0'
#6350000
0C
1@
0,
1'
#6375000
1)
#6400000
16
0@
1,
0'
#6450000
06
b0 !
b0 ?
b0 Q
b101 $
b101 <
b101 L
b1 "
b1 >
b1 P
1O
1K
1C
1@
1'
#6500000
0@
0'
0)
0(
1&
#6550000
b100 $
b100 <
b100 L
b1001 !
b1001 ?
b1001 Q
1@
1'
#6600000
0@
0'
#6625000
1)
#6650000
b1000 !
b1000 ?
b1000 Q
1@
1'
#6700000
0@
0'
#6750000
b111 !
b111 ?
b111 Q
1@
1'
0)
1(
#6800000
0@
0'
#6850000
b110 !
b110 ?
b110 Q
1@
1'
#6875000
1)
#6900000
0@
0'
#6950000
b101 !
b101 ?
b101 Q
1@
1'
#7000000
0@
0'
0)
0(
0&
#7050000
b100 !
b100 ?
b100 Q
1@
1'
#7100000
0@
0'
#7125000
1)
#7150000
b11 !
b11 ?
b11 Q
1@
1'
#7200000
0@
0'
#7250000
b10 !
b10 ?
b10 Q
1@
1'
0)
1(
#7300000
0@
0'
#7350000
b1 !
b1 ?
b1 Q
1@
1'
#7375000
1)
#7400000
0@
0'
#7450000
b0 !
b0 ?
b0 Q
1@
1'
#7500000
0@
0'
0)
0(
1&
#7550000
b11 $
b11 <
b11 L
b1001 !
b1001 ?
b1001 Q
1@
1'
#7600000
0@
0'
#7625000
1)
#7650000
b1000 !
b1000 ?
b1000 Q
1@
1'
#7700000
0@
0'
#7750000
b111 !
b111 ?
b111 Q
1@
1'
0)
1(
#7800000
0@
0'
#7850000
b110 !
b110 ?
b110 Q
1@
1'
#7875000
1)
#7900000
0@
0'
#7950000
b101 !
b101 ?
b101 Q
1@
1'
#8000000
0@
0'
0)
0(
0&
#8050000
b100 !
b100 ?
b100 Q
1@
1'
#8100000
0@
0'
#8125000
1)
#8150000
b11 !
b11 ?
b11 Q
1@
1'
#8200000
0@
0'
#8250000
b10 !
b10 ?
b10 Q
1@
1'
0)
1(
#8300000
0@
0'
#8350000
b1 !
b1 ?
b1 Q
1@
1'
#8375000
1)
#8400000
0@
0'
#8450000
b0 !
b0 ?
b0 Q
1@
1'
#8500000
0@
0'
0)
0(
1&
#8550000
b10 $
b10 <
b10 L
b1001 !
b1001 ?
b1001 Q
1@
1'
#8600000
0@
0'
#8625000
1)
#8650000
b1000 !
b1000 ?
b1000 Q
1@
1'
#8700000
0@
0'
#8750000
b111 !
b111 ?
b111 Q
1@
1'
0)
1(
#8800000
0@
0'
#8850000
b110 !
b110 ?
b110 Q
1@
1'
#8875000
1)
#8900000
0@
0'
#8950000
b101 !
b101 ?
b101 Q
1@
1'
#9000000
0@
0'
0)
0(
0&
#9050000
b100 !
b100 ?
b100 Q
1@
1'
#9100000
0@
0'
#9125000
1)
#9150000
b11 !
b11 ?
b11 Q
1@
1'
#9200000
0@
0'
#9250000
b10 !
b10 ?
b10 Q
1@
1'
0)
1(
#9300000
0@
0'
#9350000
b1 !
b1 ?
b1 Q
1@
1'
#9375000
1)
#9400000
0@
0'
#9450000
b0 !
b0 ?
b0 Q
1@
1'
#9500000
0@
0'
0)
0(
1&
#9550000
b1 $
b1 <
b1 L
b1001 !
b1001 ?
b1001 Q
1@
1'
#9600000
0@
0'
#9625000
1)
#9650000
b1000 !
b1000 ?
b1000 Q
1@
1'
#9700000
0@
0'
#9750000
b111 !
b111 ?
b111 Q
1@
1'
0)
1(
#9800000
0@
0'
#9850000
b110 !
b110 ?
b110 Q
1@
1'
#9875000
1)
#9900000
0@
0'
#9950000
b101 !
b101 ?
b101 Q
1@
1'
#10000000
0@
0'
0)
0(
0&
#10050000
b100 !
b100 ?
b100 Q
1@
1'
#10100000
0@
0'
#10125000
1)
#10150000
b11 !
b11 ?
b11 Q
1@
1'
#10200000
0@
0'
#10250000
b10 !
b10 ?
b10 Q
1@
1'
0)
1(
#10300000
0@
0'
#10350000
b1 !
b1 ?
b1 Q
1@
1'
#10375000
1)
#10400000
0@
0'
#10450000
b0 !
b0 ?
b0 Q
1@
1'
#10500000
0@
0'
0)
0(
1&
#10550000
b0 $
b0 <
b0 L
b1001 !
b1001 ?
b1001 Q
1@
1'
#10600000
0@
0'
#10625000
1)
#10650000
b1000 !
b1000 ?
b1000 Q
1@
1'
#10700000
0@
0'
#10750000
b111 !
b111 ?
b111 Q
1@
1'
0)
1(
#10800000
0@
0'
#10850000
b110 !
b110 ?
b110 Q
1@
1'
#10875000
1)
#10900000
0@
0'
#10950000
b101 !
b101 ?
b101 Q
1@
1'
#11000000
0@
0'
0)
0(
0&
#11050000
b100 !
b100 ?
b100 Q
1@
1'
#11100000
0@
0'
#11125000
1)
#11150000
b11 !
b11 ?
b11 Q
1@
1'
#11200000
0@
0'
#11250000
b10 !
b10 ?
b10 Q
1@
1'
0)
1(
#11300000
0@
0'
#11350000
b1 !
b1 ?
b1 Q
1@
1'
#11375000
1)
#11400000
0@
0'
#11450000
b0 !
b0 ?
b0 Q
1@
1'
#11500000
0@
0'
0)
0(
1&
#11550000
b0 "
b0 >
b0 P
b1001 $
b1001 <
b1001 L
b1001 !
b1001 ?
b1001 Q
1@
1'
#11600000
0@
0'
#11625000
1)
#11650000
b1000 !
b1000 ?
b1000 Q
1@
1'
#11700000
0@
0'
#11750000
b111 !
b111 ?
b111 Q
1@
1'
0)
1(
#11800000
0@
0'
#11850000
b110 !
b110 ?
b110 Q
1@
1'
#11875000
1)
#11900000
0@
0'
#11950000
b101 !
b101 ?
b101 Q
1@
1'
#12000000
0@
0'
0)
0(
0&
#12050000
b100 !
b100 ?
b100 Q
1@
1'
#12100000
0@
0'
#12125000
1)
#12150000
b11 !
b11 ?
b11 Q
1@
1'
#12200000
0@
0'
#12250000
b10 !
b10 ?
b10 Q
1@
1'
0)
1(
#12300000
0@
0'
#12350000
b1 !
b1 ?
b1 Q
1@
1'
#12375000
1)
#12400000
0@
0'
#12450000
b0 !
b0 ?
b0 Q
1@
1'
#12500000
0@
0'
0)
0(
1&
#12550000
b1000 $
b1000 <
b1000 L
b1001 !
b1001 ?
b1001 Q
1@
1'
#12600000
0@
0'
#12625000
1)
#12650000
b1000 !
b1000 ?
b1000 Q
1@
1'
#12700000
0@
0'
#12750000
b111 !
b111 ?
b111 Q
1@
1'
0)
1(
#12800000
0@
0'
#12850000
b110 !
b110 ?
b110 Q
1@
1'
#12875000
1)
#12900000
0@
0'
#12950000
b101 !
b101 ?
b101 Q
1@
1'
#13000000
0@
0'
0)
0(
0&
#13050000
b100 !
b100 ?
b100 Q
1@
1'
#13100000
0@
0'
#13125000
1)
#13150000
b11 !
b11 ?
b11 Q
1@
1'
#13200000
0@
0'
#13250000
b10 !
b10 ?
b10 Q
1@
1'
0)
1(
#13300000
0@
0'
#13350000
b1 !
b1 ?
b1 Q
1@
1'
#13375000
1)
#13400000
0@
0'
#13450000
b0 !
b0 ?
b0 Q
1@
1'
#13500000
0@
0'
0)
0(
1&
